[
  {
    "backcolor": "",
    "name": "math0ne's Gherkin"
  },
  [
    {
      "x": 3,
      "a": 7,
      "f": 6,
      "w": 4,
      "d": true
    },
    "Base Layer"
  ],
  [
    {
      "y": -0.25,
      "c": "#e8e7e3",
      "f": 3
    },
    "Q",
    "W",
    "E",
    "R",
    "T",
    "Y",
    "U",
    "I",
    "O",
    "P"
  ],
  [
    "A",
    "S",
    "D",
    "F",
    "G",
    "H",
    "J",
    "K",
    "L",
    {
      "c": "#abacab"
    },
    "Enter"
  ],
  [
    {
      "c": "#e8e7e3"
    },
    "Z\n\n\n\nCtrl",
    "X\n\n\n\nShift",
    "C\n\n\n\nAlt",
    "V\n\n\n\nFn4",
    {
      "c": "#abacab"
    },
    "Esc\n\n\n\nFn2",
    "Space\n\n\n\nFn1",
    {
      "c": "#e8e7e3"
    },
    "B\n\n\n\nFn5",
    "N\n\n\n\nFn3",
    "M\n\n\n\nCtrl",
    {
      "c": "#abacab"
    },
    "Back Space\n\n\n\nShift"
  ],
  [
    {
      "y": 0.25,
      "x": 3,
      "c": "#cccccc",
      "f": 6,
      "w": 4,
      "d": true
    },
    "Layer 1"
  ],
  [
    {
      "y": -0.25,
      "c": "#e8e7e3",
      "f": 3
    },
    "1",
    "2",
    "3",
    "4",
    "5",
    "6",
    "7",
    "8",
    "9",
    "0"
  ],
  [
    "F1",
    "F2",
    "F3",
    "F4",
    "F5",
    "F6",
    "F7",
    "F8",
    "F9",
    {
      "c": "#abacab"
    },
    "F10"
  ],
  [
    {
      "c": "#e8e7e3"
    },
    "",
    "",
    "",
    "",
    {
      "c": "#abacab"
    },
    "Del",
    "",
    {
      "c": "#e8e7e3"
    },
    "",
    "",
    "",
    {
      "c": "#abacab"
    },
    ""
  ],
  [
    {
      "y": 0.25,
      "x": 3,
      "c": "#cccccc",
      "f": 6,
      "w": 4,
      "d": true
    },
    "Layer 2"
  ],
  [
    {
      "y": -0.25,
      "c": "#e8e7e3",
      "f": 3
    },
    "!",
    "@",
    "#",
    "$",
    "%",
    "^",
    "&",
    "*",
    "(",
    ")"
  ],
  [
    "-",
    "+",
    "'",
    "\"",
    "/",
    "\\",
    ".",
    ",",
    "&uarr;",
    {
      "c": "#abacab"
    },
    ";"
  ],
  [
    {
      "c": "#e8e7e3"
    },
    "_",
    "=",
    "?",
    "|",
    {
      "c": "#abacab"
    },
    "",
    "",
    {
      "c": "#e8e7e3"
    },
    ":",
    "&larr;",
    "&darr;",
    {
      "c": "#abacab"
    },
    "&rarr;"
  ],
  [
    {
      "y": 0.25,
      "x": 3,
      "c": "#cccccc",
      "f": 6,
      "w": 4,
      "d": true
    },
    "Layer 3"
  ],
  [
    {
      "y": -0.25,
      "c": "#e8e7e3",
      "f": 3
    },
    "",
    "",
    "",
    "",
    "",
    "",
    "",
    "",
    "[",
    "]"
  ],
  [
    "Tab",
    "",
    "",
    "",
    "",
    "",
    "",
    "",
    "",
    {
      "c": "#abacab"
    },
    ""
  ],
  [
    {
      "c": "#e8e7e3"
    },
    "",
    "",
    "",
    "",
    {
      "c": "#abacab"
    },
    "",
    "",
    {
      "c": "#e8e7e3"
    },
    "",
    "",
    "",
    {
      "c": "#abacab"
    },
    ""
  ],
  [
    {
      "y": 0.25,
      "x": 3,
      "c": "#cccccc",
      "f": 6,
      "w": 4,
      "d": true
    },
    "Layer 4"
  ],
  [
    {
      "y": -0.25,
      "c": "#e8e7e3",
      "f": 3
    },
    "",
    "",
    "",
    "",
    "",
    "",
    "",
    "",
    "{",
    "}"
  ],
  [
    "Tab",
    "",
    "",
    "",
    "",
    "",
    "",
    "",
    "",
    {
      "c": "#abacab"
    },
    ""
  ],
  [
    {
      "c": "#e8e7e3"
    },
    "",
    "",
    "",
    "",
    {
      "c": "#abacab"
    },
    "",
    "",
    {
      "c": "#e8e7e3"
    },
    "Home",
    "PgDn",
    "PgUp",
    {
      "c": "#abacab"
    },
    "End"
  ],
  [
    {
      "y": 0.5,
      "x": 3,
      "c": "#cccccc",
      "f": 6,
      "w": 4,
      "d": true
    },
    "Layer 5"
  ],
  [
    {
      "y": -0.25,
      "c": "#e8e7e3",
      "f": 3
    },
    "Calc",
    "Web",
    "Mail",
    "Explore",
    "PrntScr",
    "",
    "",
    "",
    "<",
    ">"
  ],
  [
    "",
    "",
    "",
    "",
    "",
    "",
    "",
    "",
    "",
    {
      "c": "#abacab"
    },
    ""
  ],
  [
    {
      "c": "#e8e7e3"
    },
    "",
    "",
    "",
    "",
    {
      "c": "#abacab"
    },
    "Boot &nbsp;Loader",
    "",
    {
      "c": "#e8e7e3"
    },
    "",
    "",
    "",
    {
      "c": "#abacab"
    },
    ""
  ]
]